iterfzf/__init__.py
iterfzf/fzf-0.62.0-release.json
iterfzf/fzf.exe
iterfzf/test_iterfzf.py
iterfzf-1.7.0.62.0.dist-info/licenses/LICENSE
iterfzf-1.7.0.62.0.dist-info/WHEEL
iterfzf-1.7.0.62.0.dist-info/METADATA
iterfzf-1.7.0.62.0.dist-info/RECORD
