Metadata-Version: 2.4
Name: iterfzf
Version: 1.7.0.62.0
Summary: Pythonic interface to fzf
Keywords: fzf
Author-email: "Hong Minhee (洪 民憙)" <hong@minhee.org>
Requires-Python: >= 3.8
Classifier: Development Status :: 4 - Beta
Classifier: Environment :: Console :: Curses
Classifier: Intended Audience :: Developers
Classifier: License :: OSI Approved :: GNU General Public License v3 or later (GPLv3+)
Classifier: Operating System :: MacOS :: MacOS X
Classifier: Operating System :: Microsoft :: Windows
Classifier: Operating System :: POSIX :: BSD :: FreeBSD
Classifier: Operating System :: POSIX :: BSD :: OpenBSD
Classifier: Operating System :: POSIX :: Linux
Classifier: Programming Language :: Python :: 3.8
Classifier: Programming Language :: Python :: 3.9
Classifier: Programming Language :: Python :: 3.10
Classifier: Programming Language :: Python :: 3.11
Classifier: Programming Language :: Python :: 3.12
Classifier: Programming Language :: Python :: 3.13
Classifier: Programming Language :: Python :: Implementation :: CPython
Classifier: Programming Language :: Python :: Implementation :: PyPy
Classifier: Topic :: Terminals
License-File: LICENSE
Project-URL: Downloads, https://github.com/dahlia/iterfzf/releases
Project-URL: Issue Tracker, https://github.com/dahlia/iterfzf/issues
Project-URL: Source Code, https://github.com/dahlia/iterfzf
